{"is_source_file": false, "format": "", "description": "", "external_files": [], "external_methods": [], "published": [], "classes": [], "methods": [], "calls": [], "search-terms": [], "state": 2, "file_id": 119, "knowledge_revision": 343, "git_revision": "69508ad9bb8a1ec58ac468d34c394ef4f8178bd8", "hash": "3a64e77911008096887dda76eeee0756", "format-version": 4, "code-base-name": "kavia_kanbansync", "filename": "kavia_kanbansync/package.json", "revision_history": [{"343": "69508ad9bb8a1ec58ac468d34c394ef4f8178bd8"}]}