{"is_source_file": true, "format": "JavaScript", "description": "The file defines a React component named 'Column', which represents a Kanban board column. It manages the rendering of the column header, inline editing of the column title, deletion confirmation modal, and includes references to card list components.", "external_files": ["../KanbanContext", "./CardList", "./dndTypes", "../KanbanBoard"], "external_methods": ["useKanban", "updateColumn", "deleteColumn", "showToast"], "published": ["Column"], "classes": [], "methods": [{"name": "validateNewTitle(str)", "description": "Validates the new column title input for empty or unchanged titles.", "scope": "Column", "scopeKind": "function"}, {"name": "triggerTitleEdit", "description": "Starts inline editing mode for the column title."}, {"name": "saveEditTitle", "description": "Saves the new column title after validation, handles API response, and displays toast notifications."}, {"name": "handleTitleInputKey", "description": "Handles key events in the title input, triggering save or cancel actions."}, {"name": "handleDelete", "description": "Sets the modal state to prompt for column deletion."}, {"name": "doDelete", "description": "Calls the deleteColumn function and shows a toast upon success."}, {"name": "Column({ column, index, isDragging, isOver, filteredCards })", "scope": "", "scopeKind": "", "description": "unavailable"}], "calls": ["updateColumn", "deleteColumn", "showToast", "React.useState", "React.useRef", "React.useEffect", "ReactDOM.createPortal"], "search-terms": ["React Column component", "inline editing", "Kanban columns", "column title edit", "column delete modal", "drag over", "filteredCards", "column props"], "state": 2, "file_id": 106, "knowledge_revision": 357, "git_revision": "d02e1b3d1dd5190f389eadc19d646b1ec43bcf50", "revision_history": [{"314": "d02e1b3d1dd5190f389eadc19d646b1ec43bcf50"}, {"357": "d02e1b3d1dd5190f389eadc19d646b1ec43bcf50"}], "ctags": [{"_type": "tag", "name": "Column", "path": "/home/kavia/workspace/code-generation/Kavia-kanban/kavia_kanbansync/src/components/Column.js", "pattern": "/^function Column({ column, index, isDragging, isOver, filteredCards }) {$/", "language": "JavaScript", "kind": "function", "signature": "({ column, index, isDragging, isOver, filteredCards })"}, {"_type": "tag", "name": "column", "path": "/home/kavia/workspace/code-generation/Kavia-kanban/kavia_kanbansync/src/components/Column.js", "pattern": "/^        data-column-id={column.id}$/", "language": "JavaScript", "kind": "field", "scope": "data", "scopeKind": "class"}, {"_type": "tag", "name": "title}", "path": "/home/kavia/workspace/code-generation/Kavia-kanban/kavia_kanbansync/src/components/Column.js", "pattern": "/^        aria-label={`Kanban Column: ${column.title}`}$/", "language": "JavaScript", "kind": "field", "scope": "Column.aria.Kanban Column: ${column", "scopeKind": "class"}, {"_type": "tag", "name": "validateNewTitle", "path": "/home/kavia/workspace/code-generation/Kavia-kanban/kavia_kanbansync/src/components/Column.js", "pattern": "/^  function validateNewTitle(str) {$/", "language": "JavaScript", "kind": "function", "signature": "(str)", "scope": "Column", "scopeKind": "function"}], "hash": "98d266a95aa1be8ac697935387fca492", "format-version": 4, "code-base-name": "kavia_kanbansync", "filename": "kavia_kanbansync/src/components/Column.js", "fields": [{"name": "data-column-id={column.id}", "scope": "data", "scopeKind": "class", "description": "unavailable"}, {"name": "aria-label={`Kanban Column: ${column.title}`}", "scope": "Column.aria.Kanban Column: ${column", "scopeKind": "class", "description": "unavailable"}]}